xfinity_usage/__init__.py
xfinity_usage/version.py
xfinity_usage/xfinity_usage.py
xfinity_usage/tests/__init__.py
xfinity_usage/tests/test_version.py
xfinity_usage/tests/test_xfinity_usage.py
xfinity_usage-3.0.1.dist-info/METADATA
xfinity_usage-3.0.1.dist-info/RECORD
xfinity_usage-3.0.1.dist-info/WHEEL
xfinity_usage-3.0.1.dist-info/entry_points.txt
xfinity_usage-3.0.1.dist-info/top_level.txt
