Metadata-Version: 2.1
Name: xfinity-usage
Version: 3.0.1
Summary: Python/selenium script to get Xfinity bandwidth usage from Xfinity MyAccount website.
Home-page: https://github.com/jantman/xfinity-usage
Author: Jason Antman
Author-email: jason@jasonantman.com
License: UNKNOWN
Keywords: comcast xfinity usage data meter bandwidth
Platform: UNKNOWN
Classifier: Development Status :: 5 - Production/Stable
Classifier: Environment :: Console
Classifier: Intended Audience :: End Users/Desktop
Classifier: License :: OSI Approved :: GNU Affero General Public License v3 or later (AGPLv3+)
Classifier: Natural Language :: English
Classifier: Operating System :: OS Independent
Classifier: Programming Language :: Python
Classifier: Programming Language :: Python :: 2.7
Classifier: Programming Language :: Python :: 3
Classifier: Topic :: Home Automation
Classifier: Topic :: Internet
Classifier: Topic :: System :: Monitoring
Classifier: Topic :: System :: Networking :: Monitoring
Requires-Dist: selenium
